fastapi_x402/__init__.py
fastapi_x402/core.py
fastapi_x402/dependencies.py
fastapi_x402/facilitator.py
fastapi_x402/middleware.py
fastapi_x402/models.py
fastapi_x402/networks.py
fastapi_x402-0.1.7.dist-info/licenses/LICENSE
fastapi_x402-0.1.7.dist-info/METADATA
fastapi_x402-0.1.7.dist-info/WHEEL
fastapi_x402-0.1.7.dist-info/top_level.txt
fastapi_x402-0.1.7.dist-info/RECORD
