Metadata-Version: 2.4
Name: fastapi-x402
Version: 0.1.7
Summary: One-liner x402 pay-per-request for FastAPI endpoints
Author-email: FastAPI x402 <hello@fastapi-x402.dev>
License: MIT
Project-URL: Homepage, https://github.com/jordo1138/fastapi-x402
Project-URL: Repository, https://github.com/jordo1138/fastapi-x402.git
Project-URL: Issues, https://github.com/jordo1138/fastapi-x402/issues
Keywords: fastapi,x402,payments,crypto,web3,stablecoin
Classifier: Development Status :: 4 - Beta
Classifier: Intended Audience :: Developers
Classifier: Programming Language :: Python :: 3
Classifier: Programming Language :: Python :: 3.10
Classifier: Programming Language :: Python :: 3.11
Classifier: Programming Language :: Python :: 3.12
Classifier: Framework :: FastAPI
Requires-Python: >=3.10
License-File: LICENSE
Requires-Dist: fastapi>=0.68.0
Requires-Dist: httpx>=0.24.0
Requires-Dist: pydantic>=2.0.0
Requires-Dist: python-dotenv>=1.0.0
Requires-Dist: cdp-sdk>=0.0.7
Provides-Extra: dev
Requires-Dist: pytest>=7.0.0; extra == "dev"
Requires-Dist: pytest-asyncio>=0.21.0; extra == "dev"
Requires-Dist: black>=23.0.0; extra == "dev"
Requires-Dist: isort>=5.12.0; extra == "dev"
Requires-Dist: mypy>=1.0.0; extra == "dev"
Requires-Dist: pre-commit>=3.0.0; extra == "dev"
Dynamic: license-file
